.coveragerc
.editorconfig
.gitignore
.travis.yml
LICENSE
README.md
pyproject.toml
requirements.txt
requirements_dev.txt
setup.cfg
setup.py
.github/workflows/python-publish.yml
democritus_uuids/__init__.py
democritus_uuids/uuids.py
democritus_uuids.egg-info/PKG-INFO
democritus_uuids.egg-info/SOURCES.txt
democritus_uuids.egg-info/dependency_links.txt
democritus_uuids.egg-info/requires.txt
democritus_uuids.egg-info/top_level.txt
democritus_uuids.egg-info/zip-safe
tests/__init__.py
tests/test_uuids.py