Metadata-Version: 2.1
Name: democritus-uuids
Version: 2021.1.21
Summary: Democritus functions for working with uuids.
Home-page: https://github.com/democritus-project/democritus-uuids
Author: Floyd Hightower
Author-email: floyd.hightower27@gmail.com
License: MIT license
Keywords: python,utility,uuids,uuid-utility,democritus
Platform: UNKNOWN
Classifier: Development Status :: 2 - Pre-Alpha
Classifier: Intended Audience :: Developers
Classifier: License :: OSI Approved :: MIT License
Classifier: Natural Language :: English
Classifier: Programming Language :: Python :: 3
Classifier: Programming Language :: Python :: 3.4
Classifier: Programming Language :: Python :: 3.5
Classifier: Programming Language :: Python :: 3.6
Classifier: Programming Language :: Python :: 3.7
Classifier: Programming Language :: Python :: 3.8
Classifier: Programming Language :: Python :: 3.9
